.travis.yml
AUTHORS
ChangeLog
LICENSE
README.md
requirements.txt
setup.cfg
setup.py
test_skeleton/__init__.py
test_skeleton/__main__.py
test_skeleton/cli.py
test_skeleton/parse.py
test_skeleton/skeleton.py
test_skeleton.egg-info/PKG-INFO
test_skeleton.egg-info/SOURCES.txt
test_skeleton.egg-info/dependency_links.txt
test_skeleton.egg-info/not-zip-safe
test_skeleton.egg-info/pbr.json
test_skeleton.egg-info/top_level.txt
tests/__init__.py
tests/test_integration.py
tests/data/input/1.py
tests/data/output/1.txt