Metadata-Version: 1.1
Name: test-skeleton
Version: 0.1.2
Summary: a tool for creating a skeleton for Python unit tests based on source code
Home-page: https://github.com/jerry-git/test-skeleton
Author: Jerry Pussinen
Author-email: jerry.pussinen@gmail.com
License: UNKNOWN
Platform: UNKNOWN
Classifier: License :: OSI Approved :: MIT License
Classifier: Programming Language :: Python
Classifier: Programming Language :: Python :: 3
Classifier: Programming Language :: Python :: 3.5
Classifier: Programming Language :: Python :: 3.6
